pouet.py
pouet-0.1.0.dist-info/METADATA
pouet-0.1.0.dist-info/WHEEL
pouet-0.1.0.dist-info/top_level.txt
pouet-0.1.0.dist-info/RECORD
