Metadata-Version: 2.1
Name: pouet
Version: 0.1.0
Summary: Adds some pouet in your python!
Author-email: Ithilan <ithilan@ithilan.fr>
Project-URL: Homepage, https://github.com/pypa/pouet
Classifier: Programming Language :: Python :: 3
Classifier: License :: OSI Approved :: MIT License
Classifier: Operating System :: OS Independent
Requires-Python: >=3.10
